Metadata-Version: 2.1
Name: Topsis-Jaii-102003457
Version: 1.0.0
Summary: A package -> Calculates Topsis Score and Rank them accordingly
Author: Jai Mehrotra
Author-email: jmehrotra_be20@thapar.edu
License: MIT
Classifier: Programming Language :: Python :: 3
Classifier: License :: OSI Approved :: MIT License
Classifier: Operating System :: OS Independent
License-File: LICENSE.txt
Requires-Dist: pandas
